Lab04/alu.v
//Registration numbers : E/22/054 (Danuja), E/22/058 (Tharuka)
//Lab02 Task 01 : AlU module 
`timescale 1ns/1ps  //1ns - the unit of mesurement   1ps - the percision

module add_unit (A,B,Add_result);       //creating add module
    input [7:0] A,B ;                   // get input A and B as 8 bit  
    output [7:0] Add_result;            // assign output Add_result as 8 bit 
    assign  #2 Add_result = A+B;        //assigning add_result as A+B after 2 time unit
endmodule

module forward_unit (A , forward_result);       //creating forward module
    input [7:0] A;                              
    output [7:0] forward_result;
    assign #1 forward_result = A;               //forward A to forward_result after 1 time unit 
endmodule

module and_unit (A,B,And_result);               // creating add module
    input [7:0] A,B ;                       
    output [7:0] And_result;
    assign  #1 And_result = A & B;              //assign A and B as And_module after 1 time unit
endmodule

module or_unit (A,B,or_result);                 //creating or module 
    input [7:0] A,B ;
    output [7:0] or_result;
    assign  #1 or_result = A | B;               //assign A or B as or_result after 1 time unit
endmodule



module alu(DATA1, DATA2, RESULT, ZERO, SELECT); // LAB 04 MODIFICATION: added ZERO port
    input [7:0] DATA1 , DATA2 ;                 // assign 8 bit DATA1 and DATA2 as inputs
    input [2:0] SELECT;                         // assign 3 bit SELECT as a input
    output reg [7:0] RESULT;                    //assign 8 bit RESULT as a output
    output ZERO;                                // LAB 04 MODIFICATION: ZERO flag output

    wire [7:0] add_wire , forward_wire , and_wire, or_wire;         //creating 8 bit wires to carry data internally
    
    // LAB 04 MODIFICATION: Set ZERO to 1 if RESULT is exactly 0
    assign ZERO = (RESULT == 8'b00000000) ? 1'b1 : 1'b0;
    
    add_unit add_gate (DATA1,DATA2, add_wire);              // creating a add module inside ALU
    forward_unit forward_gate (DATA2, forward_wire);        // creating a forward module inside the ALU module
    and_unit and_gate (DATA1,DATA2, and_wire);              //creating a and module inside the ALU
    or_unit or_gate (DATA1,DATA2, or_wire);                 //creating a or module inside ALU

    always @(*) begin                                   //create always block
        case (SELECT)                               //creating a case block to check SELECT and to give the right output
            3'b000 : RESULT = forward_wire;         // if SELECT = 000 then result should be forward function
            3'b001 : RESULT = add_wire;             // if SELECT = 001 then do add function
            3'b010 : RESULT = and_wire;             // if SELECT = 010 then do the and function
            3'b011 : RESULT = or_wire;              // if SELECT = 011 then do or function
            default: RESULT = 8'b00000000;     //add a default as all bits are 0 for safty of the multiplexer
        endcase  
    end
endmodule

Lab04/cpu.v
// CO2070 Computer Architecture- Lab 4
//Registration numbers : E/22/054 (Danuja), E/22/058 (Tharuka)


`timescale 1ns/1ps  //1ns - the unit of mesurement   1ps - the percision

module pc_register (clk,reset,pc_in,pc_out);       //creating pc register module
    input clk, reset;                
    input [31:0] pc_in;            
    output reg [31:0] pc_out;        

    always @(posedge clk) begin
        if (reset) begin
            #1 pc_out <= 32'h0;    // Reset back to address 0 after 1 time unit
        end else begin
            #1 pc_out <= pc_in;    // Load next instruction address after 1 time unit
        end
    end

endmodule

module control_unit (opcode, RegWrite, ALUOP, Op2Select, JUMP, BRANCH);   // LAB 04 MODIFICATION: added JUMP and BRANCH ports
    input [7:0] opcode;                 //declare opcode as 8 bit input port
    output reg RegWrite;                //decleare RegWrite as output reg port
    output reg [2:0] ALUOP;             //declare ALUOP as a 3-bit output reg port
    output reg [1:0] Op2Select;         //declare Op2Select as a 2-bit output reg port
    output reg JUMP;                    // LAB 04 MODIFICATION: JUMP control signal
    output reg BRANCH;                  // LAB 04 MODIFICATION: BRANCH control signal

    always @(*) begin
        #1;                             //add a 1 unit timing delay

        RegWrite = 0;                   //set RegWrite as 0 in default 
        ALUOP = 3'b000;                 //set ALUOP as 000 in default
        Op2Select = 2'b00;              //set Op2Select as 00 in default
        JUMP = 0;                       // LAB 04 MODIFICATION: set JUMP to 0 by default
        BRANCH = 0;                     // LAB 04 MODIFICATION: set BRANCH to 0 by default

        case (opcode)                   //start a case to check opcode value

            8'h00: begin                // if opcode is 8'h00,          //load immediate
                RegWrite = 1;           //set RegWrite to 1 (because loadi writes back to a register)
                ALUOP = 3'b000;         // set ALUOP to 000 (FORWARD)
                Op2Select = 2'b10;      // set Op2Select to 10 (selects immediate value field [7:0])
            end
                
            8'h01: begin                //if opcode is 8'h01,           //MOV instruction
                RegWrite = 1;           //set RegWrite to 1 (because mov writes back to a register)
                ALUOP = 3'b000;         // set ALUOP to 000 (FORWARD)
                Op2Select = 2'b00;      // set Op2Select to 00 (selects standard Register OUT2)
            end
            
            8'h02: begin                //if opcode is 8'h02,           //ADD
                RegWrite = 1;           //set RegWrite to 1 (because add writes back to a register)
                ALUOP = 3'b001;         // set ALUOP to 001 (ADD operation)
                Op2Select = 2'b00;      // set Op2Select to 00 (selects standard Register OUT2)
            end
            
            8'h03: begin                //if opcode is 8'h03,            //SUB
                RegWrite = 1;           //set RegWrite to 1 (because sub writes back to a register)
                ALUOP = 3'b001;         // set ALUOP to 001 (ADD operation - computes OUT1 + (-OUT2))
                Op2Select = 2'b01;      // set Op2Select to 01 (selects 2's Complement negated Register OUT2)
            end

            8'h04: begin                //if opcode is 8'h04,           //AND
                RegWrite = 1;           //set RegWrite to 1 (because and writes back to a register)
                ALUOP = 3'b010;         // set ALUOP to 010 (AND operation)
                Op2Select = 2'b00;      // set Op2Select to 00 (selects standard Register OUT2)    
            end
            
            8'h05: begin                //if opcode is 8'h05,           //OR    
                RegWrite = 1;           //set RegWrite to 1 (because or writes back to a register)
                ALUOP = 3'b011;         // set ALUOP to 011 (OR operation)
                Op2Select = 2'b00;      // set Op2Select to 00 (selects standard Register OUT2)
            end

            8'h06: begin                // LAB 04 MODIFICATION: J instruction (0x06)
                JUMP = 1;               // set JUMP to 1
                // RegWrite=0, ALUOP=0, Op2Select=0 by default
            end
            
            8'h07: begin                // LAB 04 MODIFICATION: BEQ instruction (0x07)
                BRANCH = 1;             // set BRANCH to 1
                ALUOP = 3'b001;         // set ALUOP to 001 (ADD operation - computes OUT1 + (-OUT2))
                Op2Select = 2'b01;      // set Op2Select to 01 (selects 2's Complement negated Register OUT2 to perform subtraction)
            end

        endcase
    end
endmodule

module negator (in_val, out_val);       //create negator module
    input [7:0] in_val;                 //make in_val as a 8-bit input port
    output [7:0] out_val;               //make a out_val as 8-bit output port

    assign #1 out_val = ~in_val + 8'h01;        //assign the 2's complement negative of in_val to out_val after a delay of 1 time unit
endmodule

module cpu (PC, INSTRUCTION, CLK, RESET);
    
    output [31:0] PC;                       // Declare PC as a 32-bit output wire port (drives the Program Counter output)
    
    input [31:0] INSTRUCTION;               //  Declare INSTRUCTION as a 32-bit input port (carries the instruction from memory)
    
    input CLK, RESET;                       //  Declare CLK and RESET as 1-bit input ports

    // --- INTERNAL WIRE DECLARATIONS ---
    
    wire [31:0] pc_next;                    // Declare a 32-bit wire named 'pc_next'
    
    wire reg_write;                         // Declare a 1-bit wire named 'reg_write'
    
    wire [2:0] alu_op;                      // Declare a 3-bit wire named 'alu_op'
    
    wire [1:0] op2_select;                  // Declare a 2-bit wire named 'op2_select'
    
    wire [7:0] out1;                        // Declare an 8-bit wire named 'out1'
    
    wire [7:0] out2;                        // Declare an 8-bit wire named 'out2'
   
    wire [7:0] out2_neg;                    // Declare an 8-bit wire named 'out2_neg'
    
    wire [7:0] alu_in2;                     //  Declare an 8-bit wire named 'alu_in2'
    
    wire [7:0] alu_result;                  // Declare an 8-bit wire named 'alu_result'

    wire [31:0] pc_target;                  // LAB 04 MODIFICATION: Declare wire for branch/jump target address
    
    wire [31:0] pc_next_final;              // LAB 04 MODIFICATION: Declare wire for final PC value to load
    
    wire jump, branch, zero;                // LAB 04 MODIFICATION: Declare control and status wires

    
    assign #1 pc_next = PC + 32'h4;         // Increment PC by 4 to point to the next instruction (assuming 4-byte instruction width)

    // LAB 04 MODIFICATION: Branch/Jump Target Adder (latency #2)
    // Shift offset (bits 23:16) left by 2 and sign-extend, then add to pc_next
    assign #2 pc_target = pc_next + {{22{INSTRUCTION[23]}}, INSTRUCTION[23:16], 2'b00};

    // LAB 04 MODIFICATION: PC Source Multiplexer
    assign pc_next_final = (jump | (branch & zero)) ? pc_target : pc_next;

    assign alu_in2 = (op2_select == 2'b00) ? out2 :                 // if op2_select is 00, select out2
                 (op2_select == 2'b01) ? out2_neg :                 // if op2_select is 01, select out2_neg
                 (op2_select == 2'b10) ? INSTRUCTION[7:0] :         // if op2_select is 10, select the immediate value from instruction[7:0]
                 8'h00;                                         // if op2_select is anything else, select 8'h00 (default case)

   

    pc_register pc_reg_inst (.clk(CLK), .reset(RESET), .pc_in(pc_next_final), .pc_out(PC));       // LAB 04 MODIFICATION: changed pc_in to pc_next_final

    control_unit cu_inst (.opcode(INSTRUCTION[31:24]), .RegWrite(reg_write), .ALUOP(alu_op), .Op2Select(op2_select), .JUMP(jump), .BRANCH(branch));       // LAB 04 MODIFICATION: added JUMP and BRANCH

    reg_file rf_inst (                      //initiate the reg_file module with instance name rf_inst and connect the ports accordingly
        .IN(alu_result),
        .OUT1(out1),
        .OUT2(out2),
        .INADDRESS(INSTRUCTION[18:16]),
        .OUT1ADDRESS(INSTRUCTION[10:8]),
        .OUT2ADDRESS(INSTRUCTION[2:0]),
        .WRITE(reg_write),
        .CLK(CLK),
        .RESET(RESET)
    );

    negator neg_inst (.in_val(out2), .out_val(out2_neg));       //instantiate the 'negator' module with instance name neg_inst and connect the ports accordingly

    alu alu_inst (.DATA1(out1), .DATA2(alu_in2), .RESULT(alu_result), .ZERO(zero), .SELECT(alu_op));     // LAB 04 MODIFICATION: added ZERO connection

endmodule

Lab07/reg_file.v
// Registration numbers  : E/22/054 (Danuja), E/22/058 (Tharuka)
// Lab02 Task 02:  register file.

`timescale 1ns/1ps

module reg_file(
    input [7:0] IN,             // data input to write
    output [7:0] OUT1,          // asynchronous read data output 1 and output 2
    output [7:0] OUT2,             
    input [2:0] INADDRESS,      // register address to write
    input [2:0] OUT1ADDRESS,    // register address to read for OUT1 and OUT2
    input [2:0] OUT2ADDRESS, 
    input WRITE,                // write enable control signal
    input CLK,                  //  clock signal 
    input RESET                 // reset signal for synchronous clear
);

   
    reg [7:0] registers [7:0];    // Represent the 8 registers as eight 8-bit registers

    always @(posedge CLK) begin                 //synchronous to the positive edge of the clock
        if (RESET) begin
            registers[0] <= #1 8'd0;            //clear all 8 registers to zero on clock edge
            registers[1] <= #1 8'd0;
            registers[2] <= #1 8'd0;
            registers[3] <= #1 8'd0;
            registers[4] <= #1 8'd0;
            registers[5] <= #1 8'd0;
            registers[6] <= #1 8'd0;
            registers[7] <= #1 8'd0;
        end else if (WRITE) begin
            registers[INADDRESS] <= #1 IN;      // Synchronously write input data into the specified register
        end
    end

    assign #2 OUT1 = registers[OUT1ADDRESS];        // Reading values from specified registers occurs asynchronously
    assign #2 OUT2 = registers[OUT2ADDRESS];        //update the outputs OUT1 and OUT2 after a delay of #2

    // GTKWave Debugging Wires (To easily see individual registers)
    wire [7:0] r0 = registers[0];
    wire [7:0] r1 = registers[1];
    wire [7:0] r2 = registers[2];
    wire [7:0] r3 = registers[3];
    wire [7:0] r4 = registers[4];
    wire [7:0] r5 = registers[5];
    wire [7:0] r6 = registers[6];
    wire [7:0] r7 = registers[7];

endmodule

Lab04/cpu_tb.v
// Computer Architecture (CO2070) - Lab 03
// Design: Testbench of Integrated CPU of Simple Processor
// Author: Isuru Nawinne
`timescale 1ns/1ps  //1ns - the unit of mesurement   1ps - the percision

module cpu_tb;

    reg CLK, RESET;
    wire [31:0] PC;
    wire [31:0] INSTRUCTION;
    
    /* 
    ------------------------
     SIMPLE INSTRUCTION MEM
    ------------------------
    */
    
    // TODO: Initialize an array of registers (8x1024) named 'instr_mem' to be used as instruction memory
    reg [7:0] instr_mem [0:1023];

    // TODO: Create combinational logic to support CPU instruction fetching, given the Program Counter(PC) value 
    //       (make sure you include the delay for instruction fetching here)
    assign #2 INSTRUCTION = {instr_mem[PC+3], instr_mem[PC+2], instr_mem[PC+1], instr_mem[PC]};



    initial
    begin
        // Initialize instruction memory with the set of instructions you need execute on CPU
        
        // METHOD 1: manually loading instructions to instr_mem
        //{instr_mem[10'd3], instr_mem[10'd2], instr_mem[10'd1], instr_mem[10'd0]} = 32'b00000000000001000000000000000101;
        //{instr_mem[10'd7], instr_mem[10'd6], instr_mem[10'd5], instr_mem[10'd4]} = 32'b00000000000000100000000000001001;
        //{instr_mem[10'd11], instr_mem[10'd10], instr_mem[10'd9], instr_mem[10'd8]} = 32'b00000010000001100000010000000010;
        
        // METHOD 2: loading instr_mem content from instr_mem.mem file
        $readmemb("instr_mem.mem", instr_mem);
    end
    
    /* 
    -----
     CPU
    -----
    */
    cpu mycpu(PC, INSTRUCTION, CLK, RESET);

    initial
    begin
    
        // generate files needed to plot the waveform using GTKWave
        $dumpfile("cpu_wavedata.vcd");
		$dumpvars(0, cpu_tb);
        
        CLK = 1'b0;
        RESET = 1'b0;
        
        // TODO: Reset the CPU (by giving a pulse to RESET signal) to start the program execution
        #5 RESET = 1'b1; // assert reset
        #10 RESET = 1'b0; // de-assert reset
        // finish simulation after some time
        #500
        $finish;
        
    end
    
    // clock signal generation
    always
        #4 CLK = ~CLK;
        

endmodule

Lab04/cpu_wavedata.vcd
$date
	Sun Jun 14 23:04:05 2026
$end
$version
	Icarus Verilog
$end
$timescale
	1ps
$end
$scope module cpu_tb $end
$var wire 32 ! PC [31:0] $end
$var wire 32 " INSTRUCTION [31:0] $end
$var reg 1 # CLK $end
$var reg 1 $ RESET $end
$scope module mycpu $end
$var wire 1 # CLK $end
$var wire 32 % INSTRUCTION [31:0] $end
$var wire 1 $ RESET $end
$var wire 1 & zero $end
$var wire 1 ' reg_write $end
$var wire 32 ( pc_target [31:0] $end
$var wire 32 ) pc_next_final [31:0] $end
$var wire 32 * pc_next [31:0] $end
$var wire 8 + out2_neg [7:0] $end
$var wire 8 , out2 [7:0] $end
$var wire 8 - out1 [7:0] $end
$var wire 2 . op2_select [1:0] $end
$var wire 1 / jump $end
$var wire 1 0 branch $end
$var wire 8 1 alu_result [7:0] $end
$var wire 3 2 alu_op [2:0] $end
$var wire 8 3 alu_in2 [7:0] $end
$var wire 32 4 PC [31:0] $end
$scope module alu_inst $end
$var wire 8 5 DATA2 [7:0] $end
$var wire 8 6 or_wire [7:0] $end
$var wire 8 7 forward_wire [7:0] $end
$var wire 8 8 and_wire [7:0] $end
$var wire 8 9 add_wire [7:0] $end
$var wire 1 & ZERO $end
$var wire 3 : SELECT [2:0] $end
$var wire 8 ; DATA1 [7:0] $end
$var reg 8 < RESULT [7:0] $end
$scope module add_gate $end
$var wire 8 = B [7:0] $end
$var wire 8 > Add_result [7:0] $end
$var wire 8 ? A [7:0] $end
$upscope $end
$scope module and_gate $end
$var wire 8 @ And_result [7:0] $end
$var wire 8 A B [7:0] $end
$var wire 8 B A [7:0] $end
$upscope $end
$scope module forward_gate $end
$var wire 8 C A [7:0] $end
$var wire 8 D forward_result [7:0] $end
$upscope $end
$scope module or_gate $end
$var wire 8 E B [7:0] $end
$var wire 8 F or_result [7:0] $end
$var wire 8 G A [7:0] $end
$upscope $end
$upscope $end
$scope module cu_inst $end
$var wire 8 H opcode [7:0] $end
$var reg 3 I ALUOP [2:0] $end
$var reg 1 0 BRANCH $end
$var reg 1 / JUMP $end
$var reg 2 J Op2Select [1:0] $end
$var reg 1 ' RegWrite $end
$upscope $end
$scope module neg_inst $end
$var wire 8 K out_val [7:0] $end
$var wire 8 L in_val [7:0] $end
$upscope $end
$scope module pc_reg_inst $end
$var wire 1 # clk $end
$var wire 32 M pc_in [31:0] $end
$var wire 1 $ reset $end
$var reg 32 N pc_out [31:0] $end
$upscope $end
$scope module rf_inst $end
$var wire 1 # CLK $end
$var wire 8 O IN [7:0] $end
$var wire 3 P INADDRESS [2:0] $end
$var wire 8 Q OUT1 [7:0] $end
$var wire 3 R OUT1ADDRESS [2:0] $end
$var wire 8 S OUT2 [7:0] $end
$var wire 3 T OUT2ADDRESS [2:0] $end
$var wire 1 $ RESET $end
$var wire 1 ' WRITE $end
$upscope $end
$upscope $end
$upscope $end
$enddefinitions $end
$comment Show the parameter values. $end
$dumpall
$end
#0
$dumpvars
bx T
bx S
bx R
bx Q
bx P
bx O
bx N
bx M
bx L
bx K
bx J
bx I
bx H
bx G
bx F
bx E
bx D
bx C
bx B
bx A
bx @
bx ?
bx >
bx =
bx <
bx ;
bx :
bx 9
bx 8
bx 7
bx 6
bx 5
bx 4
bx 3
bx 2
bx 1
x0
x/
bx .
bx -
bx ,
bx +
bx *
bx )
bx (
x'
x&
bx %
0$
0#
bx "
bx !
$end
#4000
1#
#5000
1$
#8000
0#
#12000
1#
#13000
b0 !
b0 4
b0 N
#14000
b100 *
#15000
b0 H
b1 P
b0 R
b101 T
b10000000000000101 "
b10000000000000101 %
0$
#16000
b100 )
b100 M
b101 3
b101 5
b101 =
b101 A
b101 C
b101 E
00
0/
b10 .
b10 J
b0 2
b0 :
b0 I
1'
0#
#17000
0&
b101 1
b101 <
b101 O
bx1x1 6
bx1x1 F
b0x0x 8
b0x0x @
b101 7
b101 D
b1000 (
b0 -
b0 ;
b0 ?
b0 B
b0 G
b0 Q
b0 ,
b0 L
b0 S
#18000
b101 6
b101 F
b0 8
b0 @
b0 +
b0 K
#19000
b101 9
b101 >
#20000
1#
#21000
b100 !
b100 4
b100 N
#22000
b1000 )
b1000 M
b1000 *
#23000
b10 P
b100000000000000101 "
b100000000000000101 %
#24000
0#
#25000
b10000 (
#28000
1#
#29000
b1000 !
b1000 4
b1000 N
#30000
b1100 )
b1100 M
b1100 *
#31000
b10 3
b10 5
b10 =
b10 A
b10 C
b10 E
b111 H
b1 P
b1 R
b10 T
b111000000010000000100000010 "
b111000000010000000100000010 %
#32000
b0 3
b0 5
b0 =
b0 A
b0 C
b0 E
b10 6
b10 F
b10 7
b10 D
b1 2
b1 :
b1 I
10
b1 .
b1 J
0'
0#
#33000
b0 6
b0 F
b0 7
b0 D
b101 -
b101 ;
b101 ?
b101 B
b101 G
b101 Q
b101 ,
b101 L
b101 S
#34000
b11111011 3
b11111011 5
b11111011 =
b11111011 A
b11111011 C
b11111011 E
b101 6
b101 F
b11111011 +
b11111011 K
#35000
b1 8
b1 @
b11111111 6
b11111111 F
b11111011 7
b11111011 D
#36000
b10000 )
b10000 M
1&
b0 1
b0 <
b0 O
b0 9
b0 >
1#
#37000
b10000 !
b10000 4
b10000 N
#38000
b10100 *
#39000
b110 H
b0 R
b0 T
b110000000010000000000000000 "
b110000000010000000000000000 %
#40000
0&
b101 3
b101 5
b101 =
b101 A
b101 C
b101 E
b11111011 1
b11111011 <
b11111011 O
b11000 )
b11000 M
1/
00
b0 .
b0 J
b0 2
b0 :
b0 I
b11000 (
0#
#41000
b101 1
b101 <
b101 O
b0 3
b0 5
b0 =
b0 A
b0 C
b0 E
b101 8
b101 @
b101 6
b101 F
b101 7
b101 D
b0 -
b0 ;
b0 ?
b0 B
b0 G
b0 Q
b0 ,
b0 L
b0 S
#42000
1&
b0 1
b0 <
b0 O
b0 6
b0 F
b0 8
b0 @
b0 +
b0 K
b0 7
b0 D
#44000
1#
#45000
b11000 !
b11000 4
b11000 N
#46000
b11100 *
#47000
b10 H
b101 P
b1 R
b10 T
b10000001010000000100000010 "
b10000001010000000100000010 %
#48000
b11100 )
b11100 M
b1 2
b1 :
b1 I
1'
0/
0#
#49000
b101 3
b101 5
b101 =
b101 A
b101 C
b101 E
b110000 (
b101 -
b101 ;
b101 ?
b101 B
b101 G
b101 Q
b101 ,
b101 L
b101 S
#50000
b101 6
b101 F
b101 8
b101 @
b11111011 +
b11111011 K
b101 7
b101 D
#51000
0&
b1010 1
b1010 <
b1010 O
b1010 9
b1010 >
#52000
1#
#53000
b11100 !
b11100 4
b11100 N
#54000
b100000 )
b100000 M
b100000 *
#55000
bx H
bx P
bx R
bx T
bx "
bx %
#56000
b101 1
b101 <
b101 O
b0 2
b0 :
b0 I
0'
0#
#57000
bx 3
bx 5
bx =
bx A
bx C
bx E
bx (
bx -
bx ;
bx ?
bx B
bx G
bx Q
bx ,
bx L
bx S
#58000
x&
bx 1
bx <
bx O
bx 6
bx F
bx 8
bx @
bx +
bx K
bx 7
bx D
#59000
bx 9
bx >
#60000
1#
#61000
b100000 !
b100000 4
b100000 N
#62000
b100100 )
b100100 M
b100100 *
#64000
0#
#68000
1#
#69000
b100100 !
b100100 4
b100100 N
#70000
b101000 )
b101000 M
b101000 *
#72000
0#
#76000
1#
#77000
b101000 !
b101000 4
b101000 N
#78000
b101100 )
b101100 M
b101100 *
#80000
0#
#84000
1#
#85000
b101100 !
b101100 4
b101100 N
#86000
b110000 )
b110000 M
b110000 *
#88000
0#
#92000
1#
#93000
b110000 !
b110000 4
b110000 N
#94000
b110100 )
b110100 M
b110100 *
#96000
0#
#100000
1#
#101000
b110100 !
b110100 4
b110100 N
#102000
b111000 )
b111000 M
b111000 *
#104000
0#
#108000
1#
#109000
b111000 !
b111000 4
b111000 N
#110000
b111100 )
b111100 M
b111100 *
#112000
0#
#116000
1#
#117000
b111100 !
b111100 4
b111100 N
#118000
b1000000 )
b1000000 M
b1000000 *
#120000
0#
#124000
1#
#125000
b1000000 !
b1000000 4
b1000000 N
#126000
b1000100 )
b1000100 M
b1000100 *
#128000
0#
#132000
1#
#133000
b1000100 !
b1000100 4
b1000100 N
#134000
b1001000 )
b1001000 M
b1001000 *
#136000
0#
#140000
1#
#141000
b1001000 !
b1001000 4
b1001000 N
#142000
b1001100 )
b1001100 M
b1001100 *
#144000
0#
#148000
1#
#149000
b1001100 !
b1001100 4
b1001100 N
#150000
b1010000 )
b1010000 M
b1010000 *
#152000
0#
#156000
1#
#157000
b1010000 !
b1010000 4
b1010000 N
#158000
b1010100 )
b1010100 M
b1010100 *
#160000
0#
#164000
1#
#165000
b1010100 !
b1010100 4
b1010100 N
#166000
b1011000 )
b1011000 M
b1011000 *
#168000
0#
#172000
1#
#173000
b1011000 !
b1011000 4
b1011000 N
#174000
b1011100 )
b1011100 M
b1011100 *
#176000
0#
#180000
1#
#181000
b1011100 !
b1011100 4
b1011100 N
#182000
b1100000 )
b1100000 M
b1100000 *
#184000
0#
#188000
1#
#189000
b1100000 !
b1100000 4
b1100000 N
#190000
b1100100 )
b1100100 M
b1100100 *
#192000
0#
#196000
1#
#197000
b1100100 !
b1100100 4
b1100100 N
#198000
b1101000 )
b1101000 M
b1101000 *
#200000
0#
#204000
1#
#205000
b1101000 !
b1101000 4
b1101000 N
#206000
b1101100 )
b1101100 M
b1101100 *
#208000
0#
#212000
1#
#213000
b1101100 !
b1101100 4
b1101100 N
#214000
b1110000 )
b1110000 M
b1110000 *
#216000
0#
#220000
1#
#221000
b1110000 !
b1110000 4
b1110000 N
#222000
b1110100 )
b1110100 M
b1110100 *
#224000
0#
#228000
1#
#229000
b1110100 !
b1110100 4
b1110100 N
#230000
b1111000 )
b1111000 M
b1111000 *
#232000
0#
#236000
1#
#237000
b1111000 !
b1111000 4
b1111000 N
#238000
b1111100 )
b1111100 M
b1111100 *
#240000
0#
#244000
1#
#245000
b1111100 !
b1111100 4
b1111100 N
#246000
b10000000 )
b10000000 M
b10000000 *
#248000
0#
#252000
1#
#253000
b10000000 !
b10000000 4
b10000000 N
#254000
b10000100 )
b10000100 M
b10000100 *
#256000
0#
#260000
1#
#261000
b10000100 !
b10000100 4
b10000100 N
#262000
b10001000 )
b10001000 M
b10001000 *
#264000
0#
#268000
1#
#269000
b10001000 !
b10001000 4
b10001000 N
#270000
b10001100 )
b10001100 M
b10001100 *
#272000
0#
#276000
1#
#277000
b10001100 !
b10001100 4
b10001100 N
#278000
b10010000 )
b10010000 M
b10010000 *
#280000
0#
#284000
1#
#285000
b10010000 !
b10010000 4
b10010000 N
#286000
b10010100 )
b10010100 M
b10010100 *
#288000
0#
#292000
1#
#293000
b10010100 !
b10010100 4
b10010100 N
#294000
b10011000 )
b10011000 M
b10011000 *
#296000
0#
#300000
1#
#301000
b10011000 !
b10011000 4
b10011000 N
#302000
b10011100 )
b10011100 M
b10011100 *
#304000
0#
#308000
1#
#309000
b10011100 !
b10011100 4
b10011100 N
#310000
b10100000 )
b10100000 M
b10100000 *
#312000
0#
#316000
1#
#317000
b10100000 !
b10100000 4
b10100000 N
#318000
b10100100 )
b10100100 M
b10100100 *
#320000
0#
#324000
1#
#325000
b10100100 !
b10100100 4
b10100100 N
#326000
b10101000 )
b10101000 M
b10101000 *
#328000
0#
#332000
1#
#333000
b10101000 !
b10101000 4
b10101000 N
#334000
b10101100 )
b10101100 M
b10101100 *
#336000
0#
#340000
1#
#341000
b10101100 !
b10101100 4
b10101100 N
#342000
b10110000 )
b10110000 M
b10110000 *
#344000
0#
#348000
1#
#349000
b10110000 !
b10110000 4
b10110000 N
#350000
b10110100 )
b10110100 M
b10110100 *
#352000
0#
#356000
1#
#357000
b10110100 !
b10110100 4
b10110100 N
#358000
b10111000 )
b10111000 M
b10111000 *
#360000
0#
#364000
1#
#365000
b10111000 !
b10111000 4
b10111000 N
#366000
b10111100 )
b10111100 M
b10111100 *
#368000
0#
#372000
1#
#373000
b10111100 !
b10111100 4
b10111100 N
#374000
b11000000 )
b11000000 M
b11000000 *
#376000
0#
#380000
1#
#381000
b11000000 !
b11000000 4
b11000000 N
#382000
b11000100 )
b11000100 M
b11000100 *
#384000
0#
#388000
1#
#389000
b11000100 !
b11000100 4
b11000100 N
#390000
b11001000 )
b11001000 M
b11001000 *
#392000
0#
#396000
1#
#397000
b11001000 !
b11001000 4
b11001000 N
#398000
b11001100 )
b11001100 M
b11001100 *
#400000
0#
#404000
1#
#405000
b11001100 !
b11001100 4
b11001100 N
#406000
b11010000 )
b11010000 M
b11010000 *
#408000
0#
#412000
1#
#413000
b11010000 !
b11010000 4
b11010000 N
#414000
b11010100 )
b11010100 M
b11010100 *
#416000
0#
#420000
1#
#421000
b11010100 !
b11010100 4
b11010100 N
#422000
b11011000 )
b11011000 M
b11011000 *
#424000
0#
#428000
1#
#429000
b11011000 !
b11011000 4
b11011000 N
#430000
b11011100 )
b11011100 M
b11011100 *
#432000
0#
#436000
1#
#437000
b11011100 !
b11011100 4
b11011100 N
#438000
b11100000 )
b11100000 M
b11100000 *
#440000
0#
#444000
1#
#445000
b11100000 !
b11100000 4
b11100000 N
#446000
b11100100 )
b11100100 M
b11100100 *
#448000
0#
#452000
1#
#453000
b11100100 !
b11100100 4
b11100100 N
#454000
b11101000 )
b11101000 M
b11101000 *
#456000
0#
#460000
1#
#461000
b11101000 !
b11101000 4
b11101000 N
#462000
b11101100 )
b11101100 M
b11101100 *
#464000
0#
#468000
1#
#469000
b11101100 !
b11101100 4
b11101100 N
#470000
b11110000 )
b11110000 M
b11110000 *
#472000
0#
#476000
1#
#477000
b11110000 !
b11110000 4
b11110000 N
#478000
b11110100 )
b11110100 M
b11110100 *
#480000
0#
#484000
1#
#485000
b11110100 !
b11110100 4
b11110100 N
#486000
b11111000 )
b11111000 M
b11111000 *
#488000
0#
#492000
1#
#493000
b11111000 !
b11111000 4
b11111000 N
#494000
b11111100 )
b11111100 M
b11111100 *
#496000
0#
#500000
1#
#501000
b11111100 !
b11111100 4
b11111100 N
#502000
b100000000 )
b100000000 M
b100000000 *
#504000
0#
#508000
1#
#509000
b100000000 !
b100000000 4
b100000000 N
#510000
b100000100 )
b100000100 M
b100000100 *
