Lab07/data_memory_lab6.v
/*
Module	: 256x8-bit data memory (4-Byte blocks)
Author	: Isuru Nawinne
Date    	: 30/05/2020

Description	:

This file presents a primitive data memory module for CO2070 Lab 6
This memory allows data to be read and written as 4-Byte blocks
*/

module data_memory(
	clock,
    reset,
    read,
    write,
    address,
    writedata,
    readdata,
	busywait
);
input				clock;
input           	reset;
input           	read;
input           	write;
input[5:0]      	address;
input[31:0]     	writedata;
output reg [31:0]	readdata;
output reg      	busywait;

//Declare memory array 256x8-bits 
reg [7:0] memory_array [255:0];

//Detecting an incoming memory access
reg readaccess, writeaccess;
always @(read, write)
begin
	busywait = (read || write)? 1 : 0;
	readaccess = (read && !write)? 1 : 0;
	writeaccess = (!read && write)? 1 : 0;
end

//Reading & writing
always @(posedge clock)
begin
	if(readaccess)
	begin
		readdata[7:0]   = #40 memory_array[{address,2'b00}];
		readdata[15:8]  = #40 memory_array[{address,2'b01}];
		readdata[23:16] = #40 memory_array[{address,2'b10}];
		readdata[31:24] = #40 memory_array[{address,2'b11}];
		busywait = 0;
		readaccess = 0;
	end
	if(writeaccess)
	begin
		memory_array[{address,2'b00}] = #40 writedata[7:0];
		memory_array[{address,2'b01}] = #40 writedata[15:8];
		memory_array[{address,2'b10}] = #40 writedata[23:16];
		memory_array[{address,2'b11}] = #40 writedata[31:24];
		busywait = 0;
		writeaccess = 0;
	end
end

//Reset memory
integer i;  // loop variable required for Icarus Verilog elaboration
always @(posedge reset)
begin
    if (reset)
    begin
        for (i=0;i<256; i=i+1)
            memory_array[i] = 0;
        
        busywait = 0;
		readaccess = 0;
		writeaccess = 0;
    end
end

endmodule

Lab03/CPU Programming Tools-20260529/alu.v
//Registration numbers : E/22/054 (Danuja), E/22/058 (Tharuka)
//Lab02 Task 01 : AlU module 
`timescale 1ns/1ps  //1ns - the unit of mesurement   1ps - the percision

module add_unit (A,B,Add_result);       //creating add module
    input [7:0] A,B ;                   // get input A and B as 8 bit  
    output [7:0] Add_result;            // assign output Add_result as 8 bit 
    assign  #2 Add_result = A+B;        //assigning add_result as A+B after 2 time unit
endmodule

module forward_unit (A , forward_result);       //creating forward module
    input [7:0] A;                              
    output [7:0] forward_result;
    assign #1 forward_result = A;               //forward A to forward_result after 1 time unit 
endmodule

module and_unit (A,B,And_result);               // creating add module
    input [7:0] A,B ;                       
    output [7:0] And_result;
    assign  #1 And_result = A & B;              //assign A and B as And_module after 1 time unit
endmodule

module or_unit (A,B,or_result);                 //creating or module 
    input [7:0] A,B ;
    output [7:0] or_result;
    assign  #1 or_result = A | B;               //assign A or B as or_result after 1 time unit
endmodule



module alu(DATA1, DATA2, RESULT, SELECT);       //creating super module (ALU module)
    input [7:0] DATA1 , DATA2 ;                 // assign 8 bit DATA1 and DATA2 as inputs
    input [2:0] SELECT;                         // assign 3 bit SELECT as a input
    output reg [7:0] RESULT;                    //assign 8 bit RESULT as a output

    wire [7:0] add_wire , forward_wire , and_wire, or_wire;         //creating 8 bit wires to carry data internally
    
    add_unit add_gate (DATA1,DATA2, add_wire);              // creating a add module inside ALU
    forward_unit forward_gate (DATA2, forward_wire);        // creating a forward module inside the ALU module
    and_unit and_gate (DATA1,DATA2, and_wire);              //creating a and module inside the ALU
    or_unit or_gate (DATA1,DATA2, or_wire);                 //creating a or module inside ALU

    always @(*) begin                                   //create always block
        case (SELECT)                               //creating a case block to check SELECT and to give the right output
            3'b000 : RESULT = forward_wire;         // if SELECT = 000 then result should be forward function
            3'b001 : RESULT = add_wire;             // if SELECT = 001 then do add function
            3'b010 : RESULT = and_wire;             // if SELECT = 010 then do the and function
            3'b011 : RESULT = or_wire;              // if SELECT = 011 then do or function
            default: RESULT = 8'b00000000;     //add a default as all bits are 0 for safty of the multiplexer
        endcase  
    end
endmodule

Lab03/CPU Programming Tools-20260529/cpu.v
// CO2070 Computer Architecture- Lab 3 
//Registration numbers : E/22/054 (Danuja), E/22/058 (Tharuka)


`timescale 1ns/1ps  //1ns - the unit of mesurement   1ps - the percision

module pc_register (clk,reset,pc_in,pc_out);       //creating pc register module
    input clk, reset;                
    input [31:0] pc_in;            
    output reg [31:0] pc_out;        

    always @(posedge clk) begin
        if (reset) begin
            #1 pc_out <= 32'h0;    // Reset back to address 0 after 1 time unit
        end else begin
            #1 pc_out <= pc_in;    // Load next instruction address after 1 time unit
        end
    end

endmodule

module control_unit (opcode, RegWrite, ALUOP, Op2Select);   // creating control unit module
    input [7:0] opcode;                 //declare opcode as 8 bit input port
    output reg RegWrite;                //decleare RegWrite as output reg port
    output reg [2:0] ALUOP;             //declare ALUOP as a 3-bit output reg port
    output reg [1:0] Op2Select;         //declare Op2Select as a 2-bit output reg port

    always @(*) begin
        #1;                             //add a 1 unit timing delay

        RegWrite = 0;                   //set RegWrite as 0 in default 
        ALUOP = 3'b000;                 //set ALUOP as 000 in default
        Op2Select = 2'b00;              //set Op2Select as 00 in default

        case (opcode)                   //start a case to check opcode value

            8'h00: begin                // if opcode is 8'h00,          //load immediate
                RegWrite = 1;           //set RegWrite to 1 (because loadi writes back to a register)
                ALUOP = 3'b000;         // set ALUOP to 000 (FORWARD)
                Op2Select = 2'b10;      // set Op2Select to 10 (selects immediate value field [7:0])
            end
                
            8'h01: begin                //if opcode is 8'h01,           //MOV instruction
                RegWrite = 1;           //set RegWrite to 1 (because mov writes back to a register)
                ALUOP = 3'b000;         // set ALUOP to 000 (FORWARD)
                Op2Select = 2'b00;      // set Op2Select to 00 (selects standard Register OUT2)
            end
            
            8'h02: begin                //if opcode is 8'h02,           //ADD
                RegWrite = 1;           //set RegWrite to 1 (because add writes back to a register)
                ALUOP = 3'b001;         // set ALUOP to 001 (ADD operation)
                Op2Select = 2'b00;      // set Op2Select to 00 (selects standard Register OUT2)
            end
            
            8'h03: begin                //if opcode is 8'h03,            //SUB
                RegWrite = 1;           //set RegWrite to 1 (because sub writes back to a register)
                ALUOP = 3'b001;         // set ALUOP to 001 (ADD operation - computes OUT1 + (-OUT2))
                Op2Select = 2'b01;      // set Op2Select to 01 (selects 2's Complement negated Register OUT2)
            end

            8'h04: begin                //if opcode is 8'h04,           //AND
                RegWrite = 1;           //set RegWrite to 1 (because and writes back to a register)
                ALUOP = 3'b010;         // set ALUOP to 010 (AND operation)
                Op2Select = 2'b00;      // set Op2Select to 00 (selects standard Register OUT2)    
            end
            
            8'h05: begin                //if opcode is 8'h05,           //OR    
                RegWrite = 1;           //set RegWrite to 1 (because or writes back to a register)
                ALUOP = 3'b011;         // set ALUOP to 011 (OR operation)
                Op2Select = 2'b00;      // set Op2Select to 00 (selects standard Register OUT2)
            end

        endcase
    end
endmodule

module negator (in_val, out_val);       //create negator module
    input [7:0] in_val;                 //make in_val as a 8-bit input port
    output [7:0] out_val;               //make a out_val as 8-bit output port

    assign #1 out_val = ~in_val + 8'h01;        //assign the 2's complement negative of in_val to out_val after a delay of 1 time unit
endmodule

module cpu (PC, INSTRUCTION, CLK, RESET);
    
    output [31:0] PC;                       // Declare PC as a 32-bit output wire port (drives the Program Counter output)
    
    input [31:0] INSTRUCTION;               //  Declare INSTRUCTION as a 32-bit input port (carries the instruction from memory)
    
    input CLK, RESET;                       //  Declare CLK and RESET as 1-bit input ports

    // --- INTERNAL WIRE DECLARATIONS ---
    
    wire [31:0] pc_next;                    // Declare a 32-bit wire named 'pc_next'
    
    wire reg_write;                         // Declare a 1-bit wire named 'reg_write'
    
    wire [2:0] alu_op;                      // Declare a 3-bit wire named 'alu_op'
    
    wire [1:0] op2_select;                  // Declare a 2-bit wire named 'op2_select'
    
    wire [7:0] out1;                        // Declare an 8-bit wire named 'out1'
    
    wire [7:0] out2;                        // Declare an 8-bit wire named 'out2'
   
    wire [7:0] out2_neg;                    // Declare an 8-bit wire named 'out2_neg'
    
    wire [7:0] alu_in2;                     //  Declare an 8-bit wire named 'alu_in2'
    
    wire [7:0] alu_result;                  // Declare an 8-bit wire named 'alu_result'

    
    assign #1 pc_next = PC + 32'h4;         // Increment PC by 4 to point to the next instruction (assuming 4-byte instruction width)


    assign alu_in2 = (op2_select == 2'b00) ? out2 :                 // if op2_select is 00, select out2
                 (op2_select == 2'b01) ? out2_neg :                 // if op2_select is 01, select out2_neg
                 (op2_select == 2'b10) ? INSTRUCTION[7:0] :         // if op2_select is 10, select the immediate value from instruction[7:0]
                 8'h00;                                         // if op2_select is anything else, select 8'h00 (default case)

   

    pc_register pc_reg_inst (.clk(CLK), .reset(RESET), .pc_in(pc_next), .pc_out(PC));       // Instantiate the 'pc_register' module and connect the ports accordingly

    control_unit cu_inst (.opcode(INSTRUCTION[31:24]), .RegWrite(reg_write), .ALUOP(alu_op), .Op2Select(op2_select));       // Instantiate the 'control_unit' module and connect the ports accordingly

    reg_file rf_inst (                      //initiate the reg_file module with instance name rf_inst and connect the ports accordingly
        .IN(alu_result),
        .OUT1(out1),
        .OUT2(out2),
        .INADDRESS(INSTRUCTION[18:16]),
        .OUT1ADDRESS(INSTRUCTION[10:8]),
        .OUT2ADDRESS(INSTRUCTION[2:0]),
        .WRITE(reg_write),
        .CLK(CLK),
        .RESET(RESET)
    );

    negator neg_inst (.in_val(out2), .out_val(out2_neg));       //instantiate the 'negator' module with instance name neg_inst and connect the ports accordingly

    alu alu_inst (.DATA1(out1), .DATA2(alu_in2), .RESULT(alu_result), .SELECT(alu_op));     //instantiate the 'alu' module with instance name alu_inst and connect the ports accordingly

endmodule

Lab07/reg_file.v
// Registration numbers  : E/22/054 (Danuja), E/22/058 (Tharuka)
// Lab02 Task 02:  register file.

`timescale 1ns/1ps

module reg_file(
    input [7:0] IN,             // data input to write
    output [7:0] OUT1,          // asynchronous read data output 1 and output 2
    output [7:0] OUT2,             
    input [2:0] INADDRESS,      // register address to write
    input [2:0] OUT1ADDRESS,    // register address to read for OUT1 and OUT2
    input [2:0] OUT2ADDRESS, 
    input WRITE,                // write enable control signal
    input CLK,                  //  clock signal 
    input RESET                 // reset signal for synchronous clear
);

   
    reg [7:0] registers [7:0];    // Represent the 8 registers as eight 8-bit registers

    always @(posedge CLK) begin                 //synchronous to the positive edge of the clock
        if (RESET) begin
            registers[0] <= #1 8'd0;            //clear all 8 registers to zero on clock edge
            registers[1] <= #1 8'd0;
            registers[2] <= #1 8'd0;
            registers[3] <= #1 8'd0;
            registers[4] <= #1 8'd0;
            registers[5] <= #1 8'd0;
            registers[6] <= #1 8'd0;
            registers[7] <= #1 8'd0;
        end else if (WRITE) begin
            registers[INADDRESS] <= #1 IN;      // Synchronously write input data into the specified register
        end
    end

    assign #2 OUT1 = registers[OUT1ADDRESS];        // Reading values from specified registers occurs asynchronously
    assign #2 OUT2 = registers[OUT2ADDRESS];        //update the outputs OUT1 and OUT2 after a delay of #2

    // GTKWave Debugging Wires (To easily see individual registers)
    wire [7:0] r0 = registers[0];
    wire [7:0] r1 = registers[1];
    wire [7:0] r2 = registers[2];
    wire [7:0] r3 = registers[3];
    wire [7:0] r4 = registers[4];
    wire [7:0] r5 = registers[5];
    wire [7:0] r6 = registers[6];
    wire [7:0] r7 = registers[7];

endmodule

Lab05/cpu_tb.v
// Computer Architecture (CO2070) - Lab 03
// Design: Testbench of Integrated CPU of Simple Processor
// Author: Isuru Nawinne
`timescale 1ns/1ps  //1ns - the unit of mesurement   1ps - the percision

module cpu_tb;

    reg CLK, RESET;
    wire [31:0] PC;
    wire [31:0] INSTRUCTION;
    // LAB 5 MODIFICATION: Declare wires to interface with data memory
    wire mem_read, mem_write, mem_busywait;
    wire [7:0] mem_address, mem_writedata, mem_readdata;
    
    /* 
    ------------------------
     SIMPLE INSTRUCTION MEM
    ------------------------
    */
    
    // TODO: Initialize an array of registers (8x1024) named 'instr_mem' to be used as instruction memory
    reg [7:0] instr_mem [0:1023];

    // TODO: Create combinational logic to support CPU instruction fetching, given the Program Counter(PC) value 
    //       (make sure you include the delay for instruction fetching here)
    assign #2 INSTRUCTION = {instr_mem[PC+3], instr_mem[PC+2], instr_mem[PC+1], instr_mem[PC]};



    initial
    begin
        // Initialize instruction memory with the set of instructions you need execute on CPU
        
        // METHOD 1: manually loading instructions to instr_mem
        //{instr_mem[10'd3], instr_mem[10'd2], instr_mem[10'd1], instr_mem[10'd0]} = 32'b00000000000001000000000000000101;
        //{instr_mem[10'd7], instr_mem[10'd6], instr_mem[10'd5], instr_mem[10'd4]} = 32'b00000000000000100000000000001001;
        //{instr_mem[10'd11], instr_mem[10'd10], instr_mem[10'd9], instr_mem[10'd8]} = 32'b00000010000001100000010000000010;
        
        // METHOD 2: loading instr_mem content from instr_mem.mem file
        $readmemb("instr_mem.mem", instr_mem);
        // Lab 5 modification: TODO - Update your instr_mem.mem with a test program that uses the new instructions!
    end
    
    /* 
    -----
     CPU
    -----
    */
    // LAB 5 MODIFICATION: Update cpu instantiation to connect the new data memory wires
    cpu mycpu(PC, INSTRUCTION, CLK, RESET, mem_read, mem_write, mem_address, mem_writedata, mem_readdata, mem_busywait);

    // LAB 5 MODIFICATION: Instantiate data_memory (from lab05.v) and connect it to the wires
    data_memory mydatamem(CLK, RESET, mem_read, mem_write, mem_address, mem_writedata, mem_readdata, mem_busywait);

    initial
    begin
    
        // generate files needed to plot the waveform using GTKWave
        $dumpfile("cpu_wavedata.vcd");
		$dumpvars(0, cpu_tb);
        
        CLK = 1'b0;
        RESET = 1'b0;
        
        // TODO: Reset the CPU (by giving a pulse to RESET signal) to start the program execution
        #5 RESET = 1'b1; // assert reset
        #10 RESET = 1'b0; // de-assert reset
        // finish simulation after some time
        #500
        $finish;
        
    end
    
    // clock signal generation
    always
        #4 CLK = ~CLK;
        

endmodule

Lab03/CPU Programming Tools-20260529/cpu_wavedata.vcd
$date
	Tue Jun 09 08:51:55 2026
$end
$version
	Icarus Verilog
$end
$timescale
	1ps
$end
$scope module cpu_tb $end
$var wire 32 ! PC [31:0] $end
$var wire 32 " INSTRUCTION [31:0] $end
$var reg 1 # CLK $end
$var reg 1 $ RESET $end
$scope module mycpu $end
$var wire 1 # CLK $end
$var wire 32 % INSTRUCTION [31:0] $end
$var wire 1 $ RESET $end
$var wire 1 & reg_write $end
$var wire 32 ' pc_next [31:0] $end
$var wire 8 ( out2_neg [7:0] $end
$var wire 8 ) out2 [7:0] $end
$var wire 8 * out1 [7:0] $end
$var wire 2 + op2_select [1:0] $end
$var wire 8 , alu_result [7:0] $end
$var wire 3 - alu_op [2:0] $end
$var wire 8 . alu_in2 [7:0] $end
$var wire 32 / PC [31:0] $end
$scope module alu_inst $end
$var wire 8 0 DATA2 [7:0] $end
$var wire 8 1 or_wire [7:0] $end
$var wire 8 2 forward_wire [7:0] $end
$var wire 8 3 and_wire [7:0] $end
$var wire 8 4 add_wire [7:0] $end
$var wire 3 5 SELECT [2:0] $end
$var wire 8 6 DATA1 [7:0] $end
$var reg 8 7 RESULT [7:0] $end
$scope module add_gate $end
$var wire 8 8 B [7:0] $end
$var wire 8 9 Add_result [7:0] $end
$var wire 8 : A [7:0] $end
$upscope $end
$scope module and_gate $end
$var wire 8 ; And_result [7:0] $end
$var wire 8 < B [7:0] $end
$var wire 8 = A [7:0] $end
$upscope $end
$scope module forward_gate $end
$var wire 8 > A [7:0] $end
$var wire 8 ? forward_result [7:0] $end
$upscope $end
$scope module or_gate $end
$var wire 8 @ B [7:0] $end
$var wire 8 A or_result [7:0] $end
$var wire 8 B A [7:0] $end
$upscope $end
$upscope $end
$scope module cu_inst $end
$var wire 8 C opcode [7:0] $end
$var reg 3 D ALUOP [2:0] $end
$var reg 2 E Op2Select [1:0] $end
$var reg 1 & RegWrite $end
$upscope $end
$scope module neg_inst $end
$var wire 8 F out_val [7:0] $end
$var wire 8 G in_val [7:0] $end
$upscope $end
$scope module pc_reg_inst $end
$var wire 1 # clk $end
$var wire 32 H pc_in [31:0] $end
$var wire 1 $ reset $end
$var reg 32 I pc_out [31:0] $end
$upscope $end
$scope module rf_inst $end
$var wire 1 # CLK $end
$var wire 8 J IN [7:0] $end
$var wire 3 K INADDRESS [2:0] $end
$var wire 8 L OUT1 [7:0] $end
$var wire 3 M OUT1ADDRESS [2:0] $end
$var wire 8 N OUT2 [7:0] $end
$var wire 3 O OUT2ADDRESS [2:0] $end
$var wire 1 $ RESET $end
$var wire 1 & WRITE $end
$upscope $end
$upscope $end
$upscope $end
$enddefinitions $end
$comment Show the parameter values. $end
$dumpall
$end
#0
$dumpvars
bx O
bx N
bx M
bx L
bx K
bx J
bx I
bx H
bx G
bx F
bx E
bx D
bx C
bx B
bx A
bx @
bx ?
bx >
bx =
bx <
bx ;
bx :
bx 9
bx 8
bx 7
bx 6
bx 5
bx 4
bx 3
bx 2
bx 1
bx 0
bx /
bx .
bx -
bx ,
bx +
bx *
bx )
bx (
bx '
x&
bx %
0$
0#
bx "
bx !
$end
#4000
1#
#5000
1$
#8000
0#
#12000
1#
#13000
b0 !
b0 /
b0 I
#14000
b100 '
b100 H
#15000
b0 C
b100 K
b0 M
b101 O
b1000000000000000101 "
b1000000000000000101 %
0$
#16000
b101 .
b101 0
b101 8
b101 <
b101 >
b101 @
b10 +
b10 E
b0 -
b0 5
b0 D
1&
0#
#17000
b101 ,
b101 7
b101 J
bx1x1 1
bx1x1 A
b0x0x 3
b0x0x ;
b101 2
b101 ?
b0 *
b0 6
b0 :
b0 =
b0 B
b0 L
b0 )
b0 G
b0 N
#18000
b101 1
b101 A
b0 3
b0 ;
b0 (
b0 F
#19000
b101 4
b101 9
#20000
1#
#21000
b100 !
b100 /
b100 I
#22000
b1000 '
b1000 H
#23000
b1001 .
b1001 0
b1001 8
b1001 <
b1001 >
b1001 @
b10 K
b1 O
b100000000000001001 "
b100000000000001001 %
#24000
b1001 ,
b1001 7
b1001 J
b1001 1
b1001 A
b1001 2
b1001 ?
0#
#25000
b1001 4
b1001 9
#28000
1#
#29000
b1000 !
b1000 /
b1000 I
#30000
b1100 '
b1100 H
#31000
b10 .
b10 0
b10 8
b10 <
b10 >
b10 @
b10 C
b110 K
b100 M
b10 O
b10000001100000010000000010 "
b10000001100000010000000010 %
#32000
b0 .
b0 0
b0 8
b0 <
b0 >
b0 @
b10 1
b10 A
b10 2
b10 ?
b1 -
b1 5
b1 D
b0 +
b0 E
1&
0#
#33000
b1001 .
b1001 0
b1001 8
b1001 <
b1001 >
b1001 @
b0 1
b0 A
b0 2
b0 ?
b101 *
b101 6
b101 :
b101 =
b101 B
b101 L
b1001 )
b1001 G
b1001 N
#34000
b1101 1
b1101 A
b1 3
b1 ;
b11110111 (
b11110111 F
b1001 2
b1001 ?
#35000
b1110 ,
b1110 7
b1110 J
b1110 4
b1110 9
#36000
1#
#37000
b1100 !
b1100 /
b1100 I
#38000
b10000 '
b10000 H
#39000
b1 C
b0 K
b0 M
b110 O
b1000000000000000000000110 "
b1000000000000000000000110 %
#40000
b1001 ,
b1001 7
b1001 J
b0 -
b0 5
b0 D
1&
0#
#41000
b1110 .
b1110 0
b1110 8
b1110 <
b1110 >
b1110 @
b0 *
b0 6
b0 :
b0 =
b0 B
b0 L
b1110 )
b1110 G
b1110 N
#42000
b1110 ,
b1110 7
b1110 J
b1110 1
b1110 A
b0 3
b0 ;
b11110010 (
b11110010 F
b1110 2
b1110 ?
#44000
1#
#45000
b10000 !
b10000 /
b10000 I
#46000
b10100 '
b10100 H
#47000
b0 C
b1 K
b1 O
b10000000000000001 "
b10000000000000001 %
b1110 *
b1110 6
b1110 :
b1110 =
b1110 B
b1110 L
#48000
b1 .
b1 0
b1 8
b1 <
b1 >
b1 @
b10 +
b10 E
1&
b1110 3
b1110 ;
0#
#49000
b1 ,
b1 7
b1 J
b1111 1
b1111 A
b0 3
b0 ;
b1 2
b1 ?
b0 )
b0 G
b0 N
#50000
b0 (
b0 F
b1111 4
b1111 9
#52000
1#
#53000
b10100 !
b10100 /
b10100 I
#54000
b11000 '
b11000 H
#55000
b10 C
b10 K
b10 M
b10000000100000001000000001 "
b10000000100000001000000001 %
b1 )
b1 G
b1 N
#56000
b1111 ,
b1111 7
b1111 J
b1 -
b1 5
b1 D
b0 +
b0 E
1&
b11111111 (
b11111111 F
0#
#57000
b1001 *
b1001 6
b1001 :
b1001 =
b1001 B
b1001 L
#58000
b1001 1
b1001 A
b1 3
b1 ;
#59000
b1010 ,
b1010 7
b1010 J
b1010 4
b1010 9
#60000
1#
#61000
b11000 !
b11000 /
b11000 I
#62000
b11100 '
b11100 H
#63000
bx C
bx K
bx M
bx O
bx "
bx %
b1010 *
b1010 6
b1010 :
b1010 =
b1010 B
b1010 L
#64000
b1 ,
b1 7
b1 J
b0 -
b0 5
b0 D
0&
b1011 1
b1011 A
b0 3
b0 ;
0#
#65000
bx .
bx 0
bx 8
bx <
bx >
bx @
bx *
bx 6
bx :
bx =
bx B
bx L
bx )
bx G
bx N
b1011 4
b1011 9
#66000
bx ,
bx 7
bx J
bx 1
bx A
bx 3
bx ;
bx (
bx F
bx 2
bx ?
#67000
bx 4
bx 9
#68000
1#
#69000
b11100 !
b11100 /
b11100 I
#70000
b100000 '
b100000 H
#72000
0#
#76000
1#
#77000
b100000 !
b100000 /
b100000 I
#78000
b100100 '
b100100 H
#80000
0#
#84000
1#
#85000
b100100 !
b100100 /
b100100 I
#86000
b101000 '
b101000 H
#88000
0#
#92000
1#
#93000
b101000 !
b101000 /
b101000 I
#94000
b101100 '
b101100 H
#96000
0#
#100000
1#
#101000
b101100 !
b101100 /
b101100 I
#102000
b110000 '
b110000 H
#104000
0#
#108000
1#
#109000
b110000 !
b110000 /
b110000 I
#110000
b110100 '
b110100 H
#112000
0#
#116000
1#
#117000
b110100 !
b110100 /
b110100 I
#118000
b111000 '
b111000 H
#120000
0#
#124000
1#
#125000
b111000 !
b111000 /
b111000 I
#126000
b111100 '
b111100 H
#128000
0#
#132000
1#
#133000
b111100 !
b111100 /
b111100 I
#134000
b1000000 '
b1000000 H
#136000
0#
#140000
1#
#141000
b1000000 !
b1000000 /
b1000000 I
#142000
b1000100 '
b1000100 H
#144000
0#
#148000
1#
#149000
b1000100 !
b1000100 /
b1000100 I
#150000
b1001000 '
b1001000 H
#152000
0#
#156000
1#
#157000
b1001000 !
b1001000 /
b1001000 I
#158000
b1001100 '
b1001100 H
#160000
0#
#164000
1#
#165000
b1001100 !
b1001100 /
b1001100 I
#166000
b1010000 '
b1010000 H
#168000
0#
#172000
1#
#173000
b1010000 !
b1010000 /
b1010000 I
#174000
b1010100 '
b1010100 H
#176000
0#
#180000
1#
#181000
b1010100 !
b1010100 /
b1010100 I
#182000
b1011000 '
b1011000 H
#184000
0#
#188000
1#
#189000
b1011000 !
b1011000 /
b1011000 I
#190000
b1011100 '
b1011100 H
#192000
0#
#196000
1#
#197000
b1011100 !
b1011100 /
b1011100 I
#198000
b1100000 '
b1100000 H
#200000
0#
#204000
1#
#205000
b1100000 !
b1100000 /
b1100000 I
#206000
b1100100 '
b1100100 H
#208000
0#
#212000
1#
#213000
b1100100 !
b1100100 /
b1100100 I
#214000
b1101000 '
b1101000 H
#216000
0#
#220000
1#
#221000
b1101000 !
b1101000 /
b1101000 I
#222000
b1101100 '
b1101100 H
#224000
0#
#228000
1#
#229000
b1101100 !
b1101100 /
b1101100 I
#230000
b1110000 '
b1110000 H
#232000
0#
#236000
1#
#237000
b1110000 !
b1110000 /
b1110000 I
#238000
b1110100 '
b1110100 H
#240000
0#
#244000
1#
#245000
b1110100 !
b1110100 /
b1110100 I
#246000
b1111000 '
b1111000 H
#248000
0#
#252000
1#
#253000
b1111000 !
b1111000 /
b1111000 I
#254000
b1111100 '
b1111100 H
#256000
0#
#260000
1#
#261000
b1111100 !
b1111100 /
b1111100 I
#262000
b10000000 '
b10000000 H
#264000
0#
#268000
1#
#269000
b10000000 !
b10000000 /
b10000000 I
#270000
b10000100 '
b10000100 H
#272000
0#
#276000
1#
#277000
b10000100 !
b10000100 /
b10000100 I
#278000
b10001000 '
b10001000 H
#280000
0#
#284000
1#
#285000
b10001000 !
b10001000 /
b10001000 I
#286000
b10001100 '
b10001100 H
#288000
0#
#292000
1#
#293000
b10001100 !
b10001100 /
b10001100 I
#294000
b10010000 '
b10010000 H
#296000
0#
#300000
1#
#301000
b10010000 !
b10010000 /
b10010000 I
#302000
b10010100 '
b10010100 H
#304000
0#
#308000
1#
#309000
b10010100 !
b10010100 /
b10010100 I
#310000
b10011000 '
b10011000 H
#312000
0#
#316000
1#
#317000
b10011000 !
b10011000 /
b10011000 I
#318000
b10011100 '
b10011100 H
#320000
0#
#324000
1#
#325000
b10011100 !
b10011100 /
b10011100 I
#326000
b10100000 '
b10100000 H
#328000
0#
#332000
1#
#333000
b10100000 !
b10100000 /
b10100000 I
#334000
b10100100 '
b10100100 H
#336000
0#
#340000
1#
#341000
b10100100 !
b10100100 /
b10100100 I
#342000
b10101000 '
b10101000 H
#344000
0#
#348000
1#
#349000
b10101000 !
b10101000 /
b10101000 I
#350000
b10101100 '
b10101100 H
#352000
0#
#356000
1#
#357000
b10101100 !
b10101100 /
b10101100 I
#358000
b10110000 '
b10110000 H
#360000
0#
#364000
1#
#365000
b10110000 !
b10110000 /
b10110000 I
#366000
b10110100 '
b10110100 H
#368000
0#
#372000
1#
#373000
b10110100 !
b10110100 /
b10110100 I
#374000
b10111000 '
b10111000 H
#376000
0#
#380000
1#
#381000
b10111000 !
b10111000 /
b10111000 I
#382000
b10111100 '
b10111100 H
#384000
0#
#388000
1#
#389000
b10111100 !
b10111100 /
b10111100 I
#390000
b11000000 '
b11000000 H
#392000
0#
#396000
1#
#397000
b11000000 !
b11000000 /
b11000000 I
#398000
b11000100 '
b11000100 H
#400000
0#
#404000
1#
#405000
b11000100 !
b11000100 /
b11000100 I
#406000
b11001000 '
b11001000 H
#408000
0#
#412000
1#
#413000
b11001000 !
b11001000 /
b11001000 I
#414000
b11001100 '
b11001100 H
#416000
0#
#420000
1#
#421000
b11001100 !
b11001100 /
b11001100 I
#422000
b11010000 '
b11010000 H
#424000
0#
#428000
1#
#429000
b11010000 !
b11010000 /
b11010000 I
#430000
b11010100 '
b11010100 H
#432000
0#
#436000
1#
#437000
b11010100 !
b11010100 /
b11010100 I
#438000
b11011000 '
b11011000 H
#440000
0#
#444000
1#
#445000
b11011000 !
b11011000 /
b11011000 I
#446000
b11011100 '
b11011100 H
#448000
0#
#452000
1#
#453000
b11011100 !
b11011100 /
b11011100 I
#454000
b11100000 '
b11100000 H
#456000
0#
#460000
1#
#461000
b11100000 !
b11100000 /
b11100000 I
#462000
b11100100 '
b11100100 H
#464000
0#
#468000
1#
#469000
b11100100 !
b11100100 /
b11100100 I
#470000
b11101000 '
b11101000 H
#472000
0#
#476000
1#
#477000
b11101000 !
b11101000 /
b11101000 I
#478000
b11101100 '
b11101100 H
#480000
0#
#484000
1#
#485000
b11101100 !
b11101100 /
b11101100 I
#486000
b11110000 '
b11110000 H
#488000
0#
#492000
1#
#493000
b11110000 !
b11110000 /
b11110000 I
#494000
b11110100 '
b11110100 H
#496000
0#
#500000
1#
#501000
b11110100 !
b11110100 /
b11110100 I
#502000
b11111000 '
b11111000 H
#504000
0#
#508000
1#
#509000
b11111000 !
b11111000 /
b11111000 I
#510000
b11111100 '
b11111100 H
